{
  "frames": {
    "0078.png": {
      "frame": {
        "x": 2,
        "y": 2,
        "w": 551,
        "h": 306
      },
      "rotated": false,
      "trimmed": true,
      "spriteSourceSize": {
        "x": 49,
        "y": 294,
        "w": 551,
        "h": 306
      },
      "sourceSize": {
        "w": 600,
        "h": 600
      },
      "pivot": {
        "x": 0.5,
        "y": 0.5
      }
    },
    "0075.png": {
      "frame": {
        "x": 557,
        "y": 2,
        "w": 551,
        "h": 299
      },
      "rotated": false,
      "trimmed": true,
      "spriteSourceSize": {
        "x": 49,
        "y": 301,
        "w": 551,
        "h": 299
      },
      "sourceSize": {
        "w": 600,
        "h": 600
      },
      "pivot": {
        "x": 0.5,
        "y": 0.5
      }
    },
    "0073.png": {
      "frame": {
        "x": 1112,
        "y": 2,
        "w": 551,
        "h": 294
      },
      "rotated": false,
      "trimmed": true,
      "spriteSourceSize": {
        "x": 48,
        "y": 306,
        "w": 551,
        "h": 294
      },
      "sourceSize": {
        "w": 600,
        "h": 600
      },
      "pivot": {
        "x": 0.5,
        "y": 0.5
      }
    },
    "0197.png": {
      "frame": {
        "x": 1112,
        "y": 300,
        "w": 551,
        "h": 288
      },
      "rotated": false,
      "trimmed": true,
      "spriteSourceSize": {
        "x": 4,
        "y": 7,
        "w": 551,
        "h": 288
      },
      "sourceSize": {
        "w": 600,
        "h": 600
      },
      "pivot": {
        "x": 0.5,
        "y": 0.5
      }
    },
    "0081.png": {
      "frame": {
        "x": 557,
        "y": 305,
        "w": 550,
        "h": 313
      },
      "rotated": false,
      "trimmed": true,
      "spriteSourceSize": {
        "x": 50,
        "y": 287,
        "w": 550,
        "h": 313
      },
      "sourceSize": {
        "w": 600,
        "h": 600
      },
      "pivot": {
        "x": 0.5,
        "y": 0.5
      }
    },
    "0072.png": {
      "frame": {
        "x": 2,
        "y": 312,
        "w": 550,
        "h": 291
      },
      "rotated": false,
      "trimmed": true,
      "spriteSourceSize": {
        "x": 49,
        "y": 309,
        "w": 550,
        "h": 291
      },
      "sourceSize": {
        "w": 600,
        "h": 600
      },
      "pivot": {
        "x": 0.5,
        "y": 0.5
      }
    },
    "0084.png": {
      "frame": {
        "x": 2,
        "y": 607,
        "w": 549,
        "h": 321
      },
      "rotated": false,
      "trimmed": true,
      "spriteSourceSize": {
        "x": 51,
        "y": 279,
        "w": 549,
        "h": 321
      },
      "sourceSize": {
        "w": 600,
        "h": 600
      },
      "pivot": {
        "x": 0.5,
        "y": 0.5
      }
    },
    "0200.png": {
      "frame": {
        "x": 1111,
        "y": 592,
        "w": 548,
        "h": 287
      },
      "rotated": false,
      "trimmed": true,
      "spriteSourceSize": {
        "x": 6,
        "y": 0,
        "w": 548,
        "h": 287
      },
      "sourceSize": {
        "w": 600,
        "h": 600
      },
      "pivot": {
        "x": 0.5,
        "y": 0.5
      }
    },
    "0068.png": {
      "frame": {
        "x": 555,
        "y": 622,
        "w": 547,
        "h": 282
      },
      "rotated": false,
      "trimmed": true,
      "spriteSourceSize": {
        "x": 49,
        "y": 318,
        "w": 547,
        "h": 282
      },
      "sourceSize": {
        "w": 600,
        "h": 600
      },
      "pivot": {
        "x": 0.5,
        "y": 0.5
      }
    },
    "0070.png": {
      "frame": {
        "x": 555,
        "y": 908,
        "w": 546,
        "h": 286
      },
      "rotated": false,
      "trimmed": true,
      "spriteSourceSize": {
        "x": 49,
        "y": 314,
        "w": 546,
        "h": 286
      },
      "sourceSize": {
        "w": 600,
        "h": 600
      },
      "pivot": {
        "x": 0.5,
        "y": 0.5
      }
    },
    "0069.png": {
      "frame": {
        "x": 2,
        "y": 932,
        "w": 545,
        "h": 284
      },
      "rotated": false,
      "trimmed": true,
      "spriteSourceSize": {
        "x": 50,
        "y": 316,
        "w": 545,
        "h": 284
      },
      "sourceSize": {
        "w": 600,
        "h": 600
      },
      "pivot": {
        "x": 0.5,
        "y": 0.5
      }
    },
    "0202.png": {
      "frame": {
        "x": 1106,
        "y": 883,
        "w": 542,
        "h": 281
      },
      "rotated": false,
      "trimmed": true,
      "spriteSourceSize": {
        "x": 17,
        "y": 0,
        "w": 542,
        "h": 281
      },
      "sourceSize": {
        "w": 600,
        "h": 600
      },
      "pivot": {
        "x": 0.5,
        "y": 0.5
      }
    },
    "0065.png": {
      "frame": {
        "x": 1106,
        "y": 1168,
        "w": 540,
        "h": 274
      },
      "rotated": false,
      "trimmed": true,
      "spriteSourceSize": {
        "x": 51,
        "y": 326,
        "w": 540,
        "h": 274
      },
      "sourceSize": {
        "w": 600,
        "h": 600
      },
      "pivot": {
        "x": 0.5,
        "y": 0.5
      }
    },
    "0067.png": {
      "frame": {
        "x": 551,
        "y": 1198,
        "w": 539,
        "h": 279
      },
      "rotated": false,
      "trimmed": true,
      "spriteSourceSize": {
        "x": 51,
        "y": 321,
        "w": 539,
        "h": 279
      },
      "sourceSize": {
        "w": 600,
        "h": 600
      },
      "pivot": {
        "x": 0.5,
        "y": 0.5
      }
    },
    "0066.png": {
      "frame": {
        "x": 2,
        "y": 1220,
        "w": 539,
        "h": 278
      },
      "rotated": false,
      "trimmed": true,
      "spriteSourceSize": {
        "x": 52,
        "y": 322,
        "w": 539,
        "h": 278
      },
      "sourceSize": {
        "w": 600,
        "h": 600
      },
      "pivot": {
        "x": 0.5,
        "y": 0.5
      }
    },
    "0201.png": {
      "frame": {
        "x": 2,
        "y": 1502,
        "w": 527,
        "h": 283
      },
      "rotated": false,
      "trimmed": true,
      "spriteSourceSize": {
        "x": 32,
        "y": 0,
        "w": 527,
        "h": 283
      },
      "sourceSize": {
        "w": 600,
        "h": 600
      },
      "pivot": {
        "x": 0.5,
        "y": 0.5
      }
    },
    "0210.png": {
      "frame": {
        "x": 2,
        "y": 1789,
        "w": 518,
        "h": 257
      },
      "rotated": false,
      "trimmed": true,
      "spriteSourceSize": {
        "x": 37,
        "y": 0,
        "w": 518,
        "h": 257
      },
      "sourceSize": {
        "w": 600,
        "h": 600
      },
      "pivot": {
        "x": 0.5,
        "y": 0.5
      }
    },
    "0058.png": {
      "frame": {
        "x": 524,
        "y": 1789,
        "w": 513,
        "h": 257
      },
      "rotated": false,
      "trimmed": true,
      "spriteSourceSize": {
        "x": 60,
        "y": 343,
        "w": 513,
        "h": 257
      },
      "sourceSize": {
        "w": 600,
        "h": 600
      },
      "pivot": {
        "x": 0.5,
        "y": 0.5
      }
    },
    "0057.png": {
      "frame": {
        "x": 1041,
        "y": 1789,
        "w": 523,
        "h": 256
      },
      "rotated": false,
      "trimmed": true,
      "spriteSourceSize": {
        "x": 60,
        "y": 344,
        "w": 523,
        "h": 256
      },
      "sourceSize": {
        "w": 600,
        "h": 600
      },
      "pivot": {
        "x": 0.5,
        "y": 0.5
      }
    },
    "0214.png": {
      "frame": {
        "x": 1568,
        "y": 1789,
        "w": 473,
        "h": 245
      },
      "rotated": false,
      "trimmed": true,
      "spriteSourceSize": {
        "x": 80,
        "y": 0,
        "w": 473,
        "h": 245
      },
      "sourceSize": {
        "w": 600,
        "h": 600
      },
      "pivot": {
        "x": 0.5,
        "y": 0.5
      }
    },
    "0203.png": {
      "frame": {
        "x": 533,
        "y": 1502,
        "w": 537,
        "h": 277
      },
      "rotated": false,
      "trimmed": true,
      "spriteSourceSize": {
        "x": 16,
        "y": 0,
        "w": 537,
        "h": 277
      },
      "sourceSize": {
        "w": 600,
        "h": 600
      },
      "pivot": {
        "x": 0.5,
        "y": 0.5
      }
    },
    "0204.png": {
      "frame": {
        "x": 1074,
        "y": 1481,
        "w": 530,
        "h": 275
      },
      "rotated": false,
      "trimmed": true,
      "spriteSourceSize": {
        "x": 28,
        "y": 0,
        "w": 530,
        "h": 275
      },
      "sourceSize": {
        "w": 600,
        "h": 600
      },
      "pivot": {
        "x": 0.5,
        "y": 0.5
      }
    },
    "0032.png": {
      "frame": {
        "x": 1608,
        "y": 1481,
        "w": 431,
        "h": 192
      },
      "rotated": false,
      "trimmed": true,
      "spriteSourceSize": {
        "x": 85,
        "y": 408,
        "w": 431,
        "h": 192
      },
      "sourceSize": {
        "w": 600,
        "h": 600
      },
      "pivot": {
        "x": 0.5,
        "y": 0.5
      }
    }
  },
  "meta": {
    "app": "http://free-tex-packer.com",
    "version": "0.6.7",
    "image": "texture-7.webp",
    "format": "RGBA8888",
    "size": {
      "w": 2048,
      "h": 2048
    },
    "scale": 1
  }
}